test_sc/top.v
module top(
	input clk,
	input rst_n,
	input a,
	
	output reg rise,
	output reg down
);
	
	reg a_dely;
	always @(posedge clk or posedge rst_n)
	begin
		if(~rst_n)
		begin
			rise<=0;
			down<=0;
			a_dely<=0;
		end
		else
		begin
			a_dely<=a;
			if(~a_dely&&a)
			begin
				rise<=1;
				down<=0;
			end
			else if(a_dely&~a)
			begin
				down<=1;
				rise<=0;
			end
			else
			begin
				rise<=0;
				down<=0;
			end
		end
	end
endmodule

test/wave.vcd
$version Generated by VerilatedVcd $end
$date Sun Apr  9 15:06:36 2023 $end
$timescale 1ps $end

 $scope module TOP $end
  $var wire  1 % a $end
  $var wire  1 # clk $end
  $var wire  1 ' down $end
  $var wire  1 & rise $end
  $var wire  1 $ rst_n $end
  $scope module top $end
   $var wire  1 % a $end
   $var wire  1 ( a_dely $end
   $var wire  1 # clk $end
   $var wire  1 ' down $end
   $var wire  1 & rise $end
   $var wire  1 $ rst_n $end
  $upscope $end
 $upscope $end
$enddefinitions $end


#1
1#
0$
0%
0&
0'
0(
#2
0#
#3
1#
#4
0#
#5
1#
#6
0#
#7
1#
#8
0#
#9
1#
#10
0#
1$
#11
1#
#12
0#
#13
1#
#14
0#
#15
1#
#16
0#
#17
1#
#18
0#
#19
1#
#20
0#
1%
#21
1#
1&
1(
#22
0#
#23
1#
0&
#24
0#
#25
1#
#26
0#
#27
1#
#28
0#
#29
1#
#30
0#
0%
#31
1#
1'
0(
#32
0#
#33
1#
0'
