test_sc/top.v
module top(
	input clk,
	input rst_n,
	input a,
	
	output reg rise,
	output reg down
);
	
	reg a_dely;
	always @(posedge clk or posedge rst_n)
	begin
		if(~rst_n)
		begin
			rise<=0;
			down<=0;
			a_dely<=0;
		end
		else
		begin
			a_dely<=a;
			if(~a_dely&&a)
			begin
				rise<=1;
				down<=0;
			end
			else if(a_dely&~a)
			begin
				down<=1;
				rise<=0;
			end
			else
			begin
				rise<=0;
				down<=0;
			end
		end
	end
endmodule

test_sc/wave.vcd
$version Generated by VerilatedVcd $end
$date Sun Apr  9 16:20:51 2023 $end
$timescale 1ps $end

 $scope module top $end
  $scope module top $end
   $var wire  1 % a $end
   $var wire  1 ( a_dely $end
   $var wire  1 # clk $end
   $var wire  1 ' down $end
   $var wire  1 & rise $end
   $var wire  1 $ rst_n $end
  $upscope $end
 $upscope $end
$enddefinitions $end


#0
0#
0$
0%
0&
0'
0(
#1000
1#
#2000
0#
#3000
1#
#4000
0#
#5000
1#
#6000
0#
#7000
1#
#8000
0#
#9000
1#
#10000
0#
1$
#11000
1#
#12000
0#
#13000
1#
#14000
0#
#15000
1#
#16000
0#
#17000
1#
#18000
0#
#19000
1#
#20000
0#
1%
#21000
1#
1&
1(
#22000
0#
#23000
1#
0&
#24000
0#
#25000
1#
#26000
0#
#27000
1#
#28000
0#
#29000
1#
#30000
0#
0%
#31000
1#
1'
0(
#32000
0#
#33000
1#
0'
